Metadata-Version: 1.0
Name: dada-email
Version: 0.0.9
Summary: Re-usable email utilities for dada-lake
Home-page: http://globally.ltd
Author: gltd
Author-email: hey@gltd.email
License: UNKNOWN
Platform: UNKNOWN
